Jconfig/__init__.py
Jconfig/config.py
Jconfig-1.0.dist-info/METADATA
Jconfig-1.0.dist-info/RECORD
Jconfig-1.0.dist-info/WHEEL
Jconfig-1.0.dist-info/top_level.txt
