Metadata-Version: 2.1
Name: Jconfig
Version: 1.0
Summary: Python config manager using JSON
Home-page: https://github.com/labTifo/jconfig
Author: Labreche Abdellatif
Author-email: abdellatif1898@gmail.com
License: UNKNOWN
Platform: UNKNOWN
Classifier: Programming Language :: Python :: 3
Classifier: License :: OSI Approved :: MIT License
Classifier: Operating System :: OS Independent
